ppt2gif/__init__.py
ppt2gif/png2gif.py
ppt2gif/ppt2png.py
ppt2gif-1.0.2.dist-info/METADATA
ppt2gif-1.0.2.dist-info/WHEEL
ppt2gif-1.0.2.dist-info/top_level.txt
ppt2gif-1.0.2.dist-info/RECORD
